fastagi_client/__init__.py
fastagi_client/client.py
fastagi_client/exceptions.py
fastagi_client/types.py
fastagi_client/lib/__init__.py
fastagi_client/lib/auth.py
fastagi_client/lib/fastagi.py
fastagi_client-0.0.1.dist-info/LICENSE
fastagi_client-0.0.1.dist-info/METADATA
fastagi_client-0.0.1.dist-info/WHEEL
fastagi_client-0.0.1.dist-info/top_level.txt
fastagi_client-0.0.1.dist-info/RECORD
