Metadata-Version: 2.1
Name: fastagi_client
Version: 0.0.1
Summary: Python package for Fastagi
Home-page: https://app.fastagi.khulnasoft.com
Author: KhulnaSoft
Author-email: info@khulnasoft.com
License: MIT
License-File: LICENSE
Requires-Dist: pydantic ==1.10.13
Requires-Dist: requests ==2.32.2
Requires-Dist: pytest ==7.3.2
